<?xml version="1.0" encoding="UTF-8" standalone="yes"?>
<w:document xmlns:wpc="http://schemas.microsoft.com/office/word/2010/wordprocessingCanvas" xmlns:cx="http://schemas.microsoft.com/office/drawing/2014/chartex" xmlns:cx1="http://schemas.microsoft.com/office/drawing/2015/9/8/chartex" xmlns:cx2="http://schemas.microsoft.com/office/drawing/2015/10/21/chartex" xmlns:cx3="http://schemas.microsoft.com/office/drawing/2016/5/9/chartex" xmlns:cx4="http://schemas.microsoft.com/office/drawing/2016/5/10/chartex" xmlns:cx5="http://schemas.microsoft.com/office/drawing/2016/5/11/chartex" xmlns:cx6="http://schemas.microsoft.com/office/drawing/2016/5/12/chartex" xmlns:cx7="http://schemas.microsoft.com/office/drawing/2016/5/13/chartex" xmlns:cx8="http://schemas.microsoft.com/office/drawing/2016/5/14/chartex" xmlns:mc="http://schemas.openxmlformats.org/markup-compatibility/2006" xmlns:aink="http://schemas.microsoft.com/office/drawing/2016/ink" xmlns:am3d="http://schemas.microsoft.com/office/drawing/2017/model3d" xmlns:o="urn:schemas-microsoft-com:office:office" xmlns:oel="http://schemas.microsoft.com/office/2019/extlst" xmlns:r="http://schemas.openxmlformats.org/officeDocument/2006/relationships" xmlns:m="http://schemas.openxmlformats.org/officeDocument/2006/math" xmlns:v="urn:schemas-microsoft-com:vml" xmlns:wp14="http://schemas.microsoft.com/office/word/2010/wordprocessingDrawing" xmlns:wp="http://schemas.openxmlformats.org/drawingml/2006/wordprocessingDrawing" xmlns:w10="urn:schemas-microsoft-com:office:word" xmlns:w="http://schemas.openxmlformats.org/wordprocessingml/2006/main" xmlns:w14="http://schemas.microsoft.com/office/word/2010/wordml" xmlns:w15="http://schemas.microsoft.com/office/word/2012/wordml" xmlns:w16cex="http://schemas.microsoft.com/office/word/2018/wordml/cex" xmlns:w16cid="http://schemas.microsoft.com/office/word/2016/wordml/cid" xmlns:w16="http://schemas.microsoft.com/office/word/2018/wordml" xmlns:w16du="http://schemas.microsoft.com/office/word/2023/wordml/word16du" xmlns:w16sdtdh="http://schemas.microsoft.com/office/word/2020/wordml/sdtdatahash" xmlns:w16sdtfl="http://schemas.microsoft.com/office/word/2024/wordml/sdtformatlock" xmlns:w16se="http://schemas.microsoft.com/office/word/2015/wordml/symex" xmlns:wpg="http://schemas.microsoft.com/office/word/2010/wordprocessingGroup" xmlns:wpi="http://schemas.microsoft.com/office/word/2010/wordprocessingInk" xmlns:wne="http://schemas.microsoft.com/office/word/2006/wordml" xmlns:wps="http://schemas.microsoft.com/office/word/2010/wordprocessingShape" mc:Ignorable="w14 w15 w16se w16cid w16 w16cex w16sdtdh w16sdtfl w16du wp14"><w:body><w:p w14:paraId="0472EB33" w14:textId="77777777" w:rsidR="00EF3070" w:rsidRDefault="00000000"><w:pPr><w:spacing w:after="0" w:line="360" w:lineRule="auto"/><w:jc w:val="center"/><w:rPr><w:rFonts w:ascii="Times New Roman" w:hAnsi="Times New Roman" w:cs="Times New Roman"/><w:b/><w:bCs/></w:rPr></w:pPr><w:r><w:rPr><w:rFonts w:ascii="Times New Roman" w:hAnsi="Times New Roman" w:cs="Times New Roman"/><w:b/><w:bCs/></w:rPr><w:t>MINI PROJECT SYNOPSIS (WPL)</w:t></w:r></w:p><w:p w14:paraId="47B5B461" w14:textId="77777777" w:rsidR="00EF3070" w:rsidRDefault="00EF3070"><w:pPr><w:spacing w:after="0" w:line="360" w:lineRule="auto"/><w:rPr><w:rFonts w:ascii="Times New Roman" w:hAnsi="Times New Roman" w:cs="Times New Roman"/></w:rPr></w:pPr></w:p><w:p w14:paraId="20D5D790" w14:textId="77777777" w:rsidR="00EF3070" w:rsidRDefault="00000000"><w:pPr><w:spacing w:after="0" w:line="360" w:lineRule="auto"/><w:rPr><w:rFonts w:ascii="Times New Roman" w:hAnsi="Times New Roman" w:cs="Times New Roman"/><w:b/><w:bCs/></w:rPr></w:pPr><w:r><w:rPr><w:rFonts w:ascii="Times New Roman" w:hAnsi="Times New Roman" w:cs="Times New Roman"/><w:b/><w:bCs/></w:rPr><w:t>Title of the Mini Project</w:t></w:r></w:p><w:p w14:paraId="46BB7F7C" w14:textId="77777777" w:rsidR="00EF3070" w:rsidRDefault="00000000"><w:pPr><w:pStyle w:val="BodyText"/><w:spacing w:after="0" w:line="360" w:lineRule="auto"/></w:pPr><w:bookmarkStart w:id="0" w:name="docs-internal-guid-cf52763e-7fff-63a8-ce"/><w:bookmarkEnd w:id="0"/><w:r><w:rPr><w:rFonts w:ascii="Times New Roman" w:hAnsi="Times New Roman" w:cs="Times New Roman"/><w:color w:val="000000"/><w:sz w:val="22"/></w:rPr><w:t>SMART CITY INCIDENT REPORTING SYSTEM</w:t></w:r></w:p><w:p w14:paraId="22169F86" w14:textId="77777777" w:rsidR="00EF3070" w:rsidRDefault="00EF3070"><w:pPr><w:spacing w:after="0" w:line="360" w:lineRule="auto"/><w:rPr><w:rFonts w:ascii="Times New Roman" w:hAnsi="Times New Roman" w:cs="Times New Roman"/><w:b/><w:bCs/></w:rPr></w:pPr></w:p><w:p w14:paraId="58F2AB99" w14:textId="77777777" w:rsidR="00EF3070" w:rsidRDefault="00000000"><w:pPr><w:spacing w:after="0" w:line="360" w:lineRule="auto"/><w:rPr><w:rFonts w:ascii="Times New Roman" w:hAnsi="Times New Roman" w:cs="Times New Roman"/><w:b/><w:bCs/></w:rPr></w:pPr><w:r><w:rPr><w:rFonts w:ascii="Times New Roman" w:hAnsi="Times New Roman" w:cs="Times New Roman"/><w:b/><w:bCs/></w:rPr><w:t>Technologies Used</w:t></w:r></w:p><w:p w14:paraId="70ADF734" w14:textId="77777777" w:rsidR="00EF3070" w:rsidRDefault="00000000"><w:pPr><w:pStyle w:val="BodyText"/><w:spacing w:after="0" w:line="360" w:lineRule="auto"/><w:rPr><w:rFonts w:ascii="Times New Roman" w:hAnsi="Times New Roman" w:cs="Times New Roman"/></w:rPr></w:pPr><w:bookmarkStart w:id="1" w:name="docs-internal-guid-ebce9d3a-7fff-d340-b9"/><w:bookmarkEnd w:id="1"/><w:r><w:rPr><w:rFonts w:ascii="Times New Roman" w:hAnsi="Times New Roman" w:cs="Times New Roman"/><w:color w:val="000000"/><w:sz w:val="22"/></w:rPr><w:t>HTML, CSS, JavaScript, jQuery, Bootstrap</w:t></w:r></w:p><w:p w14:paraId="5CF171F0" w14:textId="77777777" w:rsidR="00EF3070" w:rsidRDefault="00EF3070"><w:pPr><w:pStyle w:val="BodyText"/></w:pPr></w:p><w:p w14:paraId="35ACDB54" w14:textId="77777777" w:rsidR="00EF3070" w:rsidRDefault="00000000"><w:pPr><w:pStyle w:val="BodyText"/><w:spacing w:after="0" w:line="331" w:lineRule="auto"/><w:rPr><w:rFonts w:ascii="Arial;sans-serif" w:hAnsi="Arial;sans-serif"/><w:color w:val="000000"/><w:sz w:val="22"/></w:rPr></w:pPr><w:r><w:rPr><w:rFonts w:ascii="Arial;sans-serif" w:hAnsi="Arial;sans-serif"/><w:color w:val="000000"/><w:sz w:val="22"/></w:rPr><w:t>Django (Backend Framework)</w:t></w:r></w:p><w:p w14:paraId="436708DF" w14:textId="77777777" w:rsidR="00EF3070" w:rsidRDefault="00EF3070"><w:pPr><w:pStyle w:val="BodyText"/></w:pPr></w:p><w:p w14:paraId="62CC274E" w14:textId="77777777" w:rsidR="00EF3070" w:rsidRDefault="00000000"><w:pPr><w:pStyle w:val="BodyText"/><w:spacing w:after="0" w:line="331" w:lineRule="auto"/><w:rPr><w:rFonts w:ascii="Arial;sans-serif" w:hAnsi="Arial;sans-serif"/><w:color w:val="000000"/><w:sz w:val="22"/></w:rPr></w:pPr><w:r><w:rPr><w:rFonts w:ascii="Arial;sans-serif" w:hAnsi="Arial;sans-serif"/><w:color w:val="000000"/><w:sz w:val="22"/></w:rPr><w:t>Django Channels (</w:t></w:r><w:proofErr w:type="spellStart"/><w:r><w:rPr><w:rFonts w:ascii="Arial;sans-serif" w:hAnsi="Arial;sans-serif"/><w:color w:val="000000"/><w:sz w:val="22"/></w:rPr><w:t>WebSockets</w:t></w:r><w:proofErr w:type="spellEnd"/><w:r><w:rPr><w:rFonts w:ascii="Arial;sans-serif" w:hAnsi="Arial;sans-serif"/><w:color w:val="000000"/><w:sz w:val="22"/></w:rPr><w:t xml:space="preserve"> for real</w:t></w:r><w:r><w:rPr><w:rFonts w:ascii="Arial;sans-serif" w:hAnsi="Arial;sans-serif"/><w:color w:val="000000"/><w:sz w:val="22"/></w:rPr><w:noBreakHyphen/><w:t>time updates)</w:t></w:r></w:p><w:p w14:paraId="4D0CC270" w14:textId="77777777" w:rsidR="00EF3070" w:rsidRDefault="00EF3070"><w:pPr><w:pStyle w:val="BodyText"/></w:pPr></w:p><w:p w14:paraId="02D33CDB" w14:textId="05B60EB3" w:rsidR="00EF3070" w:rsidRDefault="007E1021"><w:pPr><w:pStyle w:val="BodyText"/></w:pPr><w:proofErr w:type="spellStart"/><w:r><w:rPr><w:rFonts w:ascii="Arial;sans-serif" w:hAnsi="Arial;sans-serif"/><w:color w:val="000000"/><w:sz w:val="22"/></w:rPr><w:t>Supabase</w:t></w:r><w:proofErr w:type="spellEnd"/><w:r><w:rPr><w:rFonts w:ascii="Arial;sans-serif" w:hAnsi="Arial;sans-serif"/><w:color w:val="000000"/><w:sz w:val="22"/></w:rPr><w:t xml:space="preserve"> (PostgreSQL)</w:t></w:r></w:p><w:p w14:paraId="7CD26184" w14:textId="77777777" w:rsidR="00EF3070" w:rsidRDefault="00000000"><w:pPr><w:pStyle w:val="BodyText"/><w:spacing w:after="0" w:line="331" w:lineRule="auto"/><w:rPr><w:rFonts w:ascii="Arial;sans-serif" w:hAnsi="Arial;sans-serif"/><w:color w:val="000000"/><w:sz w:val="22"/></w:rPr></w:pPr><w:r><w:rPr><w:rFonts w:ascii="Arial;sans-serif" w:hAnsi="Arial;sans-serif"/><w:color w:val="000000"/><w:sz w:val="22"/></w:rPr><w:t>Redis (Channel Layer / Caching)</w:t></w:r></w:p><w:p w14:paraId="2DF3FB7E" w14:textId="77777777" w:rsidR="00EF3070" w:rsidRDefault="00EF3070"><w:pPr><w:pStyle w:val="BodyText"/></w:pPr></w:p><w:p w14:paraId="250D1D8E" w14:textId="05CD23DC" w:rsidR="00EF3070" w:rsidRDefault="00893636"><w:pPr><w:spacing w:after="0" w:line="360" w:lineRule="auto"/><w:rPr><w:rFonts w:ascii="Times New Roman" w:hAnsi="Times New Roman" w:cs="Times New Roman"/></w:rPr></w:pPr><w:proofErr w:type="spellStart"/><w:r><w:rPr><w:rFonts w:ascii="Times New Roman" w:hAnsi="Times New Roman" w:cs="Times New Roman"/></w:rPr><w:t>MapLibre</w:t></w:r><w:proofErr w:type="spellEnd"/><w:r><w:rPr><w:rFonts w:ascii="Times New Roman" w:hAnsi="Times New Roman" w:cs="Times New Roman"/></w:rPr><w:t xml:space="preserve"> GL </w:t></w:r><w:proofErr w:type="spellStart"/><w:r><w:rPr><w:rFonts w:ascii="Times New Roman" w:hAnsi="Times New Roman" w:cs="Times New Roman"/></w:rPr><w:t>js</w:t></w:r><w:proofErr w:type="spellEnd"/><w:r><w:rPr><w:rFonts w:ascii="Times New Roman" w:hAnsi="Times New Roman" w:cs="Times New Roman"/></w:rPr><w:t xml:space="preserve"> (Map API)</w:t></w:r></w:p><w:p w14:paraId="0333918E" w14:textId="77777777" w:rsidR="00EF3070" w:rsidRDefault="00000000"><w:pPr><w:spacing w:after="0" w:line="360" w:lineRule="auto"/><w:rPr><w:rFonts w:ascii="Times New Roman" w:hAnsi="Times New Roman" w:cs="Times New Roman"/><w:b/><w:bCs/></w:rPr></w:pPr><w:r><w:rPr><w:rFonts w:ascii="Times New Roman" w:hAnsi="Times New Roman" w:cs="Times New Roman"/><w:b/><w:bCs/></w:rPr><w:t>Objectives</w:t></w:r></w:p><w:p w14:paraId="6C639434" w14:textId="77777777" w:rsidR="00EF3070" w:rsidRDefault="00000000"><w:pPr><w:pStyle w:val="BodyText"/><w:numPr><w:ilvl w:val="0"/><w:numId w:val="1"/></w:numPr><w:spacing w:after="0" w:line="360" w:lineRule="auto"/><w:rPr><w:rFonts w:ascii="Arial;sans-serif" w:hAnsi="Arial;sans-serif"/><w:color w:val="000000"/><w:sz w:val="22"/></w:rPr></w:pPr><w:bookmarkStart w:id="2" w:name="docs-internal-guid-4c09731a-7fff-9dc2-5c"/><w:bookmarkEnd w:id="2"/><w:r><w:rPr><w:rFonts w:ascii="Arial;sans-serif" w:hAnsi="Arial;sans-serif"/><w:b/><w:bCs/><w:color w:val="000000"/><w:sz w:val="22"/></w:rPr><w:t>Centralized Civic Reporting:</w:t></w:r><w:r><w:rPr><w:rFonts w:ascii="Arial;sans-serif" w:hAnsi="Arial;sans-serif"/><w:color w:val="000000"/><w:sz w:val="22"/></w:rPr><w:t xml:space="preserve"> Provide citizens a unified platform to report civic issues such as potholes, garbage overflow, streetlight failures, and water leakage.</w:t></w:r></w:p><w:p w14:paraId="433981C2" w14:textId="77777777" w:rsidR="00EF3070" w:rsidRDefault="00EF3070"><w:pPr><w:pStyle w:val="BodyText"/></w:pPr></w:p><w:p w14:paraId="1033CB6B" w14:textId="77777777" w:rsidR="00EF3070" w:rsidRDefault="00000000"><w:pPr><w:pStyle w:val="BodyText"/><w:numPr><w:ilvl w:val="0"/><w:numId w:val="1"/></w:numPr><w:spacing w:after="0" w:line="331" w:lineRule="auto"/></w:pPr><w:r><w:rPr><w:rFonts w:ascii="Arial;sans-serif" w:hAnsi="Arial;sans-serif"/><w:b/><w:bCs/><w:color w:val="000000"/><w:sz w:val="22"/></w:rPr><w:t>Real</w:t></w:r><w:r><w:rPr><w:rFonts w:ascii="Arial;sans-serif" w:hAnsi="Arial;sans-serif"/><w:b/><w:bCs/><w:color w:val="000000"/><w:sz w:val="22"/></w:rPr><w:noBreakHyphen/><w:t>Time Updates:</w:t></w:r><w:r><w:rPr><w:rFonts w:ascii="Arial;sans-serif" w:hAnsi="Arial;sans-serif"/><w:color w:val="000000"/><w:sz w:val="22"/></w:rPr><w:t xml:space="preserve"> Enable live tracking of complaint status using </w:t></w:r><w:proofErr w:type="spellStart"/><w:r><w:rPr><w:rFonts w:ascii="Arial;sans-serif" w:hAnsi="Arial;sans-serif"/><w:color w:val="000000"/><w:sz w:val="22"/></w:rPr><w:t>WebSockets</w:t></w:r><w:proofErr w:type="spellEnd"/><w:r><w:rPr><w:rFonts w:ascii="Arial;sans-serif" w:hAnsi="Arial;sans-serif"/><w:color w:val="000000"/><w:sz w:val="22"/></w:rPr><w:t xml:space="preserve"> so users can instantly see progress without refreshing the page.</w:t></w:r></w:p><w:p w14:paraId="2E0F767A" w14:textId="77777777" w:rsidR="00EF3070" w:rsidRDefault="00EF3070"><w:pPr><w:pStyle w:val="BodyText"/></w:pPr></w:p><w:p w14:paraId="2240FF6A" w14:textId="77777777" w:rsidR="00EF3070" w:rsidRDefault="00000000"><w:pPr><w:pStyle w:val="BodyText"/><w:numPr><w:ilvl w:val="0"/><w:numId w:val="1"/></w:numPr><w:spacing w:after="0" w:line="331" w:lineRule="auto"/></w:pPr><w:r><w:rPr><w:rFonts w:ascii="Arial;sans-serif" w:hAnsi="Arial;sans-serif"/><w:b/><w:bCs/><w:color w:val="000000"/><w:sz w:val="22"/></w:rPr><w:t>Efficient Government Response:</w:t></w:r><w:r><w:rPr><w:rFonts w:ascii="Arial;sans-serif" w:hAnsi="Arial;sans-serif"/><w:color w:val="000000"/><w:sz w:val="22"/></w:rPr><w:t xml:space="preserve"> Automatically route complaints to the correct municipal department based on issue type and location.</w:t></w:r></w:p><w:p w14:paraId="329337DC" w14:textId="77777777" w:rsidR="00EF3070" w:rsidRDefault="00EF3070"><w:pPr><w:pStyle w:val="BodyText"/></w:pPr></w:p><w:p w14:paraId="54D2CF28" w14:textId="77777777" w:rsidR="00EF3070" w:rsidRDefault="00000000"><w:pPr><w:pStyle w:val="BodyText"/><w:numPr><w:ilvl w:val="0"/><w:numId w:val="1"/></w:numPr><w:spacing w:after="0" w:line="331" w:lineRule="auto"/></w:pPr><w:r><w:rPr><w:rFonts w:ascii="Arial;sans-serif" w:hAnsi="Arial;sans-serif"/><w:b/><w:bCs/><w:color w:val="000000"/><w:sz w:val="22"/></w:rPr><w:t xml:space="preserve">Transparency &amp; Accountability: </w:t></w:r><w:r><w:rPr><w:rFonts w:ascii="Arial;sans-serif" w:hAnsi="Arial;sans-serif"/><w:color w:val="000000"/><w:sz w:val="22"/></w:rPr><w:t>Allow citizens to monitor resolution timelines and department responsiveness.</w:t></w:r></w:p><w:p w14:paraId="36622260" w14:textId="77777777" w:rsidR="00EF3070" w:rsidRDefault="00EF3070"><w:pPr><w:pStyle w:val="BodyText"/></w:pPr></w:p><w:p w14:paraId="6DCD857A" w14:textId="77777777" w:rsidR="00EF3070" w:rsidRDefault="00000000"><w:pPr><w:pStyle w:val="BodyText"/><w:numPr><w:ilvl w:val="0"/><w:numId w:val="1"/></w:numPr><w:spacing w:after="0" w:line="331" w:lineRule="auto"/></w:pPr><w:r><w:rPr><w:rFonts w:ascii="Arial;sans-serif" w:hAnsi="Arial;sans-serif"/><w:b/><w:bCs/><w:color w:val="000000"/><w:sz w:val="22"/></w:rPr><w:t>Data</w:t></w:r><w:r><w:rPr><w:rFonts w:ascii="Arial;sans-serif" w:hAnsi="Arial;sans-serif"/><w:b/><w:bCs/><w:color w:val="000000"/><w:sz w:val="22"/></w:rPr><w:noBreakHyphen/><w:t xml:space="preserve">Driven Governance: </w:t></w:r><w:r><w:rPr><w:rFonts w:ascii="Arial;sans-serif" w:hAnsi="Arial;sans-serif"/><w:color w:val="000000"/><w:sz w:val="22"/></w:rPr><w:t>Provide analytics dashboards for administrators to identify high</w:t></w:r><w:r><w:rPr><w:rFonts w:ascii="Arial;sans-serif" w:hAnsi="Arial;sans-serif"/><w:color w:val="000000"/><w:sz w:val="22"/></w:rPr><w:noBreakHyphen/><w:t>risk zones and recurring urban problems.</w:t></w:r></w:p><w:p w14:paraId="008699E7" w14:textId="77777777" w:rsidR="00EF3070" w:rsidRDefault="00EF3070"><w:pPr><w:spacing w:after="0" w:line="360" w:lineRule="auto"/><w:rPr><w:rFonts w:ascii="Times New Roman" w:hAnsi="Times New Roman" w:cs="Times New Roman"/></w:rPr></w:pPr></w:p><w:p w14:paraId="46CADAB4" w14:textId="77777777" w:rsidR="00EF3070" w:rsidRDefault="00000000"><w:pPr><w:spacing w:after="0" w:line="360" w:lineRule="auto"/><w:rPr><w:rFonts w:ascii="Times New Roman" w:hAnsi="Times New Roman" w:cs="Times New Roman"/><w:b/><w:bCs/></w:rPr></w:pPr><w:r><w:rPr><w:rFonts w:ascii="Times New Roman" w:hAnsi="Times New Roman" w:cs="Times New Roman"/><w:b/><w:bCs/></w:rPr><w:lastRenderedPageBreak/><w:t>Project Description</w:t></w:r></w:p><w:p w14:paraId="6F351689" w14:textId="77777777" w:rsidR="00EF3070" w:rsidRDefault="00EF3070"><w:pPr><w:spacing w:after="0" w:line="360" w:lineRule="auto"/><w:rPr><w:rFonts w:ascii="Times New Roman" w:hAnsi="Times New Roman" w:cs="Times New Roman"/><w:b/><w:bCs/></w:rPr></w:pPr></w:p><w:p w14:paraId="62AE87B2" w14:textId="77777777" w:rsidR="00EF3070" w:rsidRDefault="00000000"><w:pPr><w:pStyle w:val="BodyText"/><w:spacing w:after="0" w:line="360" w:lineRule="auto"/><w:rPr><w:rFonts w:ascii="Times New Roman" w:hAnsi="Times New Roman" w:cs="Times New Roman"/></w:rPr></w:pPr><w:bookmarkStart w:id="3" w:name="docs-internal-guid-477d3442-7fff-6b86-55"/><w:bookmarkEnd w:id="3"/><w:r><w:rPr><w:rFonts w:ascii="Times New Roman" w:hAnsi="Times New Roman" w:cs="Times New Roman"/><w:color w:val="000000"/><w:sz w:val="22"/></w:rPr><w:t>The Smart City Incident Reporting System is a web</w:t></w:r><w:r><w:rPr><w:rFonts w:ascii="Times New Roman" w:hAnsi="Times New Roman" w:cs="Times New Roman"/><w:color w:val="000000"/><w:sz w:val="22"/></w:rPr><w:noBreakHyphen/><w:t>based civic engagement platform designed to bridge the communication gap between citizens and municipal authorities. Urban residents often face challenges in reporting infrastructure problems due to fragmented communication channels and lack of transparency in complaint resolution.</w:t></w:r></w:p><w:p w14:paraId="5C98904E" w14:textId="77777777" w:rsidR="00EF3070" w:rsidRDefault="00EF3070"><w:pPr><w:pStyle w:val="BodyText"/></w:pPr></w:p><w:p w14:paraId="63E4D59A" w14:textId="77777777" w:rsidR="00EF3070" w:rsidRDefault="00000000"><w:pPr><w:pStyle w:val="BodyText"/><w:spacing w:after="0" w:line="331" w:lineRule="auto"/><w:rPr><w:rFonts w:ascii="Arial;sans-serif" w:hAnsi="Arial;sans-serif"/><w:color w:val="000000"/><w:sz w:val="22"/></w:rPr></w:pPr><w:r><w:rPr><w:rFonts w:ascii="Arial;sans-serif" w:hAnsi="Arial;sans-serif"/><w:color w:val="000000"/><w:sz w:val="22"/></w:rPr><w:t xml:space="preserve">This system enables users to submit complaints by selecting a location on the map, uploading images, and categorizing the issue. The </w:t></w:r><w:r><w:rPr><w:rFonts w:ascii="Arial;sans-serif" w:hAnsi="Arial;sans-serif"/><w:b/><w:bCs/><w:color w:val="000000"/><w:sz w:val="22"/></w:rPr><w:t>Django</w:t></w:r><w:r><w:rPr><w:rFonts w:ascii="Arial;sans-serif" w:hAnsi="Arial;sans-serif"/><w:color w:val="000000"/><w:sz w:val="22"/></w:rPr><w:t xml:space="preserve"> backend handles authentication, complaint routing, and administrative workflows, while </w:t></w:r><w:r><w:rPr><w:rFonts w:ascii="Arial;sans-serif" w:hAnsi="Arial;sans-serif"/><w:b/><w:bCs/><w:color w:val="000000"/><w:sz w:val="22"/></w:rPr><w:t xml:space="preserve">PostgreSQL </w:t></w:r><w:r><w:rPr><w:rFonts w:ascii="Arial;sans-serif" w:hAnsi="Arial;sans-serif"/><w:color w:val="000000"/><w:sz w:val="22"/></w:rPr><w:t>ensures reliable storage of geospatial and complaint data.</w:t></w:r></w:p><w:p w14:paraId="5CE369E8" w14:textId="77777777" w:rsidR="00EF3070" w:rsidRDefault="00EF3070"><w:pPr><w:pStyle w:val="BodyText"/></w:pPr></w:p><w:p w14:paraId="1B62D7E1" w14:textId="77777777" w:rsidR="00EF3070" w:rsidRDefault="00000000"><w:pPr><w:pStyle w:val="BodyText"/><w:spacing w:after="0" w:line="331" w:lineRule="auto"/><w:rPr><w:rFonts w:ascii="Arial;sans-serif" w:hAnsi="Arial;sans-serif"/><w:color w:val="000000"/><w:sz w:val="22"/></w:rPr></w:pPr><w:r><w:rPr><w:rFonts w:ascii="Arial;sans-serif" w:hAnsi="Arial;sans-serif"/><w:color w:val="000000"/><w:sz w:val="22"/></w:rPr><w:t xml:space="preserve">Using </w:t></w:r><w:proofErr w:type="spellStart"/><w:r><w:rPr><w:rFonts w:ascii="Arial;sans-serif" w:hAnsi="Arial;sans-serif"/><w:b/><w:bCs/><w:color w:val="000000"/><w:sz w:val="22"/></w:rPr><w:t>WebSockets</w:t></w:r><w:proofErr w:type="spellEnd"/><w:r><w:rPr><w:rFonts w:ascii="Arial;sans-serif" w:hAnsi="Arial;sans-serif"/><w:b/><w:bCs/><w:color w:val="000000"/><w:sz w:val="22"/></w:rPr><w:t xml:space="preserve"> </w:t></w:r><w:r><w:rPr><w:rFonts w:ascii="Arial;sans-serif" w:hAnsi="Arial;sans-serif"/><w:color w:val="000000"/><w:sz w:val="22"/></w:rPr><w:t>powered by Django Channels, citizens receive real</w:t></w:r><w:r><w:rPr><w:rFonts w:ascii="Arial;sans-serif" w:hAnsi="Arial;sans-serif"/><w:color w:val="000000"/><w:sz w:val="22"/></w:rPr><w:noBreakHyphen/><w:t>time updates whenever the complaint status changes (e.g., Submitted → Assigned → In Progress → Resolved). Authorities can update progress from their dashboard, instantly notifying the concerned user.</w:t></w:r></w:p><w:p w14:paraId="3A008A1C" w14:textId="77777777" w:rsidR="00EF3070" w:rsidRDefault="00EF3070"><w:pPr><w:pStyle w:val="BodyText"/></w:pPr></w:p><w:p w14:paraId="41BF36ED" w14:textId="77777777" w:rsidR="00EF3070" w:rsidRDefault="00000000"><w:pPr><w:pStyle w:val="BodyText"/><w:spacing w:after="0" w:line="331" w:lineRule="auto"/><w:rPr><w:rFonts w:ascii="Arial;sans-serif" w:hAnsi="Arial;sans-serif"/></w:rPr></w:pPr><w:r><w:rPr><w:rFonts w:ascii="Arial;sans-serif" w:hAnsi="Arial;sans-serif"/><w:color w:val="000000"/><w:sz w:val="22"/></w:rPr><w:t>Administrators also gain access to analytics dashboards showing heatmaps of complaints, department efficiency metrics, and average resolution time, enabling better urban planning and resource allocation.</w:t></w:r></w:p><w:p w14:paraId="5FAB0B5F" w14:textId="77777777" w:rsidR="00EF3070" w:rsidRDefault="00EF3070"><w:pPr><w:spacing w:after="0" w:line="360" w:lineRule="auto"/><w:rPr><w:rFonts w:ascii="Times New Roman" w:hAnsi="Times New Roman" w:cs="Times New Roman"/><w:b/><w:bCs/></w:rPr></w:pPr></w:p><w:p w14:paraId="3FE01D38" w14:textId="77777777" w:rsidR="00EF3070" w:rsidRDefault="00EF3070"><w:pPr><w:spacing w:after="0" w:line="360" w:lineRule="auto"/><w:rPr><w:rFonts w:ascii="Times New Roman" w:hAnsi="Times New Roman" w:cs="Times New Roman"/><w:b/><w:bCs/></w:rPr></w:pPr></w:p><w:p w14:paraId="13CDC1CA" w14:textId="77777777" w:rsidR="00EF3070" w:rsidRDefault="00000000"><w:pPr><w:spacing w:after="0" w:line="360" w:lineRule="auto"/><w:rPr><w:rFonts w:ascii="Times New Roman" w:hAnsi="Times New Roman" w:cs="Times New Roman"/><w:b/><w:bCs/></w:rPr></w:pPr><w:r><w:rPr><w:rFonts w:ascii="Times New Roman" w:hAnsi="Times New Roman" w:cs="Times New Roman"/><w:b/><w:bCs/></w:rPr><w:t>Features</w:t></w:r></w:p><w:p w14:paraId="5790310E" w14:textId="77777777" w:rsidR="00EF3070" w:rsidRDefault="00000000"><w:pPr><w:pStyle w:val="BodyText"/><w:numPr><w:ilvl w:val="0"/><w:numId w:val="2"/></w:numPr><w:spacing w:after="0" w:line="360" w:lineRule="auto"/><w:rPr><w:rFonts w:ascii="Arial;sans-serif" w:hAnsi="Arial;sans-serif"/><w:color w:val="000000"/><w:sz w:val="22"/></w:rPr></w:pPr><w:bookmarkStart w:id="4" w:name="docs-internal-guid-ff6a65d7-7fff-ce02-a4"/><w:bookmarkEnd w:id="4"/><w:r><w:rPr><w:rFonts w:ascii="Arial;sans-serif" w:hAnsi="Arial;sans-serif"/><w:b/><w:bCs/><w:color w:val="000000"/><w:sz w:val="22"/></w:rPr><w:t xml:space="preserve">User Authentication: </w:t></w:r><w:r><w:rPr><w:rFonts w:ascii="Arial;sans-serif" w:hAnsi="Arial;sans-serif"/><w:color w:val="000000"/><w:sz w:val="22"/></w:rPr><w:t>Secure citizen registration and login system.</w:t></w:r></w:p><w:p w14:paraId="51B6DBA6" w14:textId="77777777" w:rsidR="00EF3070" w:rsidRDefault="00EF3070"><w:pPr><w:pStyle w:val="BodyText"/></w:pPr></w:p><w:p w14:paraId="6F1548EB" w14:textId="77777777" w:rsidR="00EF3070" w:rsidRDefault="00000000"><w:pPr><w:pStyle w:val="BodyText"/><w:numPr><w:ilvl w:val="0"/><w:numId w:val="2"/></w:numPr><w:spacing w:after="0" w:line="331" w:lineRule="auto"/></w:pPr><w:r><w:rPr><w:rFonts w:ascii="Arial;sans-serif" w:hAnsi="Arial;sans-serif"/><w:b/><w:bCs/><w:color w:val="000000"/><w:sz w:val="22"/></w:rPr><w:t>Map</w:t></w:r><w:r><w:rPr><w:rFonts w:ascii="Arial;sans-serif" w:hAnsi="Arial;sans-serif"/><w:b/><w:bCs/><w:color w:val="000000"/><w:sz w:val="22"/></w:rPr><w:noBreakHyphen/><w:t>Based Reporting:</w:t></w:r><w:r><w:rPr><w:rFonts w:ascii="Arial;sans-serif" w:hAnsi="Arial;sans-serif"/><w:color w:val="000000"/><w:sz w:val="22"/></w:rPr><w:t xml:space="preserve"> Users select the exact incident location using an interactive map.</w:t></w:r></w:p><w:p w14:paraId="1E9B4281" w14:textId="77777777" w:rsidR="00EF3070" w:rsidRDefault="00EF3070"><w:pPr><w:pStyle w:val="BodyText"/></w:pPr></w:p><w:p w14:paraId="45530E54" w14:textId="77777777" w:rsidR="00EF3070" w:rsidRDefault="00000000"><w:pPr><w:pStyle w:val="BodyText"/><w:numPr><w:ilvl w:val="0"/><w:numId w:val="2"/></w:numPr><w:spacing w:after="0" w:line="331" w:lineRule="auto"/></w:pPr><w:r><w:rPr><w:rFonts w:ascii="Arial;sans-serif" w:hAnsi="Arial;sans-serif"/><w:b/><w:bCs/><w:color w:val="000000"/><w:sz w:val="22"/></w:rPr><w:t>Image Upload Evidence:</w:t></w:r><w:r><w:rPr><w:rFonts w:ascii="Arial;sans-serif" w:hAnsi="Arial;sans-serif"/><w:color w:val="000000"/><w:sz w:val="22"/></w:rPr><w:t xml:space="preserve"> Citizens attach photos for better issue verification.</w:t></w:r></w:p><w:p w14:paraId="1E598096" w14:textId="77777777" w:rsidR="00EF3070" w:rsidRDefault="00EF3070"><w:pPr><w:pStyle w:val="BodyText"/></w:pPr></w:p><w:p w14:paraId="6AA6CCB0" w14:textId="77777777" w:rsidR="00EF3070" w:rsidRDefault="00000000"><w:pPr><w:pStyle w:val="BodyText"/><w:numPr><w:ilvl w:val="0"/><w:numId w:val="2"/></w:numPr><w:spacing w:after="0" w:line="331" w:lineRule="auto"/></w:pPr><w:r><w:rPr><w:rFonts w:ascii="Arial;sans-serif" w:hAnsi="Arial;sans-serif"/><w:b/><w:bCs/><w:color w:val="000000"/><w:sz w:val="22"/></w:rPr><w:t>Department Routing Logic:</w:t></w:r><w:r><w:rPr><w:rFonts w:ascii="Arial;sans-serif" w:hAnsi="Arial;sans-serif"/><w:color w:val="000000"/><w:sz w:val="22"/></w:rPr><w:t xml:space="preserve"> Automatic assignment to relevant municipal department.</w:t></w:r></w:p><w:p w14:paraId="1C075FBF" w14:textId="77777777" w:rsidR="00EF3070" w:rsidRDefault="00EF3070"><w:pPr><w:pStyle w:val="BodyText"/></w:pPr></w:p><w:p w14:paraId="61F0D3C3" w14:textId="77777777" w:rsidR="00EF3070" w:rsidRDefault="00000000"><w:pPr><w:pStyle w:val="BodyText"/><w:numPr><w:ilvl w:val="0"/><w:numId w:val="2"/></w:numPr><w:spacing w:after="0" w:line="331" w:lineRule="auto"/></w:pPr><w:r><w:rPr><w:rFonts w:ascii="Arial;sans-serif" w:hAnsi="Arial;sans-serif"/><w:b/><w:bCs/><w:color w:val="000000"/><w:sz w:val="22"/></w:rPr><w:t>Real</w:t></w:r><w:r><w:rPr><w:rFonts w:ascii="Arial;sans-serif" w:hAnsi="Arial;sans-serif"/><w:b/><w:bCs/><w:color w:val="000000"/><w:sz w:val="22"/></w:rPr><w:noBreakHyphen/><w:t>Time Status Updates:</w:t></w:r><w:r><w:rPr><w:rFonts w:ascii="Arial;sans-serif" w:hAnsi="Arial;sans-serif"/><w:color w:val="000000"/><w:sz w:val="22"/></w:rPr><w:t xml:space="preserve"> WebSocket notifications when complaint status changes.</w:t></w:r></w:p><w:p w14:paraId="6EF8D493" w14:textId="77777777" w:rsidR="00EF3070" w:rsidRDefault="00EF3070"><w:pPr><w:pStyle w:val="BodyText"/></w:pPr></w:p><w:p w14:paraId="5B000B74" w14:textId="77777777" w:rsidR="00EF3070" w:rsidRDefault="00000000"><w:pPr><w:pStyle w:val="BodyText"/><w:numPr><w:ilvl w:val="0"/><w:numId w:val="2"/></w:numPr><w:spacing w:after="0" w:line="331" w:lineRule="auto"/></w:pPr><w:r><w:rPr><w:rFonts w:ascii="Arial;sans-serif" w:hAnsi="Arial;sans-serif"/><w:b/><w:bCs/><w:color w:val="000000"/><w:sz w:val="22"/></w:rPr><w:t xml:space="preserve">Live Public Dashboard: </w:t></w:r><w:r><w:rPr><w:rFonts w:ascii="Arial;sans-serif" w:hAnsi="Arial;sans-serif"/><w:color w:val="000000"/><w:sz w:val="22"/></w:rPr><w:t>Citizens can view nearby reported issues to avoid duplicates.</w:t></w:r></w:p><w:p w14:paraId="2BC44B51" w14:textId="77777777" w:rsidR="00EF3070" w:rsidRDefault="00EF3070"><w:pPr><w:pStyle w:val="BodyText"/></w:pPr></w:p><w:p w14:paraId="248A24AA" w14:textId="77777777" w:rsidR="00EF3070" w:rsidRDefault="00000000"><w:pPr><w:pStyle w:val="BodyText"/><w:numPr><w:ilvl w:val="0"/><w:numId w:val="2"/></w:numPr><w:spacing w:after="0" w:line="331" w:lineRule="auto"/></w:pPr><w:r><w:rPr><w:rFonts w:ascii="Arial;sans-serif" w:hAnsi="Arial;sans-serif"/><w:b/><w:bCs/><w:color w:val="000000"/><w:sz w:val="22"/></w:rPr><w:t xml:space="preserve">Admin Control Panel: </w:t></w:r><w:r><w:rPr><w:rFonts w:ascii="Arial;sans-serif" w:hAnsi="Arial;sans-serif"/><w:color w:val="000000"/><w:sz w:val="22"/></w:rPr><w:t>Authorities manage, assign, and update complaints.</w:t></w:r></w:p><w:p w14:paraId="62AD571C" w14:textId="77777777" w:rsidR="00EF3070" w:rsidRDefault="00EF3070"><w:pPr><w:pStyle w:val="BodyText"/></w:pPr></w:p><w:p w14:paraId="2EF3C6B5" w14:textId="77777777" w:rsidR="00EF3070" w:rsidRDefault="00000000"><w:pPr><w:pStyle w:val="BodyText"/><w:numPr><w:ilvl w:val="0"/><w:numId w:val="2"/></w:numPr><w:spacing w:after="0" w:line="331" w:lineRule="auto"/></w:pPr><w:r><w:rPr><w:rFonts w:ascii="Arial;sans-serif" w:hAnsi="Arial;sans-serif"/><w:b/><w:bCs/><w:color w:val="000000"/><w:sz w:val="22"/></w:rPr><w:t>Priority Handling:</w:t></w:r><w:r><w:rPr><w:rFonts w:ascii="Arial;sans-serif" w:hAnsi="Arial;sans-serif"/><w:color w:val="000000"/><w:sz w:val="22"/></w:rPr><w:t xml:space="preserve"> Emergency complaints receive higher priority routing.</w:t></w:r></w:p><w:p w14:paraId="591AD90E" w14:textId="77777777" w:rsidR="00EF3070" w:rsidRDefault="00EF3070"><w:pPr><w:pStyle w:val="BodyText"/></w:pPr></w:p><w:p w14:paraId="7605DCFA" w14:textId="77777777" w:rsidR="00EF3070" w:rsidRDefault="00000000"><w:pPr><w:pStyle w:val="BodyText"/><w:numPr><w:ilvl w:val="0"/><w:numId w:val="2"/></w:numPr><w:spacing w:after="0" w:line="331" w:lineRule="auto"/></w:pPr><w:r><w:rPr><w:rFonts w:ascii="Arial;sans-serif" w:hAnsi="Arial;sans-serif"/><w:b/><w:bCs/><w:color w:val="000000"/><w:sz w:val="22"/></w:rPr><w:t>Search &amp; Filter:</w:t></w:r><w:r><w:rPr><w:rFonts w:ascii="Arial;sans-serif" w:hAnsi="Arial;sans-serif"/><w:color w:val="000000"/><w:sz w:val="22"/></w:rPr><w:t xml:space="preserve"> Filter complaints by area, type, or status.</w:t></w:r></w:p><w:p w14:paraId="59FB5C6D" w14:textId="77777777" w:rsidR="00EF3070" w:rsidRDefault="00EF3070"><w:pPr><w:pStyle w:val="BodyText"/></w:pPr></w:p><w:p w14:paraId="1B15BA4F" w14:textId="77777777" w:rsidR="00EF3070" w:rsidRDefault="00000000"><w:pPr><w:pStyle w:val="BodyText"/><w:numPr><w:ilvl w:val="0"/><w:numId w:val="2"/></w:numPr><w:spacing w:after="0" w:line="331" w:lineRule="auto"/></w:pPr><w:r><w:rPr><w:rFonts w:ascii="Arial;sans-serif" w:hAnsi="Arial;sans-serif"/><w:b/><w:bCs/><w:color w:val="000000"/><w:sz w:val="22"/></w:rPr><w:t>Analytics Dashboard:</w:t></w:r><w:r><w:rPr><w:rFonts w:ascii="Arial;sans-serif" w:hAnsi="Arial;sans-serif"/><w:color w:val="000000"/><w:sz w:val="22"/></w:rPr><w:t xml:space="preserve"> Heatmaps, resolution time charts, and department performance reports.</w:t></w:r></w:p><w:p w14:paraId="2B993414" w14:textId="77777777" w:rsidR="00EF3070" w:rsidRDefault="00EF3070"><w:pPr><w:pStyle w:val="BodyText"/></w:pPr></w:p><w:p w14:paraId="2F6FB2C4" w14:textId="77777777" w:rsidR="00EF3070" w:rsidRDefault="00000000"><w:pPr><w:pStyle w:val="BodyText"/><w:numPr><w:ilvl w:val="0"/><w:numId w:val="2"/></w:numPr><w:spacing w:after="0" w:line="331" w:lineRule="auto"/></w:pPr><w:r><w:rPr><w:rFonts w:ascii="Arial;sans-serif" w:hAnsi="Arial;sans-serif"/><w:b/><w:bCs/><w:color w:val="000000"/><w:sz w:val="22"/></w:rPr><w:t xml:space="preserve">Escalation System: </w:t></w:r><w:r><w:rPr><w:rFonts w:ascii="Arial;sans-serif" w:hAnsi="Arial;sans-serif"/><w:color w:val="000000"/><w:sz w:val="22"/></w:rPr><w:t>Complaints automatically escalate if unresolved within deadline.</w:t></w:r></w:p><w:p w14:paraId="6B29D853" w14:textId="77777777" w:rsidR="00EF3070" w:rsidRDefault="00EF3070"><w:pPr><w:pStyle w:val="BodyText"/></w:pPr></w:p><w:p w14:paraId="3F5CE129" w14:textId="77777777" w:rsidR="00EF3070" w:rsidRDefault="00000000"><w:pPr><w:pStyle w:val="BodyText"/><w:numPr><w:ilvl w:val="0"/><w:numId w:val="2"/></w:numPr><w:spacing w:after="0" w:line="331" w:lineRule="auto"/></w:pPr><w:r><w:rPr><w:rFonts w:ascii="Arial;sans-serif" w:hAnsi="Arial;sans-serif"/><w:b/><w:bCs/><w:color w:val="000000"/><w:sz w:val="22"/></w:rPr><w:t>Responsive Design:</w:t></w:r><w:r><w:rPr><w:rFonts w:ascii="Arial;sans-serif" w:hAnsi="Arial;sans-serif"/><w:color w:val="000000"/><w:sz w:val="22"/></w:rPr><w:t xml:space="preserve"> Works across desktop and mobile devices.</w:t></w:r></w:p><w:p w14:paraId="6936C938" w14:textId="77777777" w:rsidR="00EF3070" w:rsidRDefault="00EF3070"><w:pPr><w:pStyle w:val="BodyText"/><w:spacing w:after="0" w:line="331" w:lineRule="auto"/><w:ind w:left="720"/><w:rPr><w:rFonts w:ascii="Arial;sans-serif" w:hAnsi="Arial;sans-serif"/><w:color w:val="000000"/><w:sz w:val="22"/></w:rPr></w:pPr></w:p><w:p w14:paraId="75D255B0" w14:textId="77777777" w:rsidR="00EF3070" w:rsidRDefault="00000000"><w:pPr><w:spacing w:after="0" w:line="360" w:lineRule="auto"/><w:rPr><w:rFonts w:ascii="Times New Roman" w:hAnsi="Times New Roman" w:cs="Times New Roman"/><w:b/><w:bCs/></w:rPr></w:pPr><w:r><w:rPr><w:rFonts w:ascii="Times New Roman" w:hAnsi="Times New Roman" w:cs="Times New Roman"/><w:b/><w:bCs/></w:rPr><w:t>Group Members:</w:t></w:r></w:p><w:tbl><w:tblPr><w:tblW w:w="8332" w:type="dxa"/><w:tblLayout w:type="fixed"/><w:tblCellMar><w:top w:w="15" w:type="dxa"/><w:left w:w="15" w:type="dxa"/><w:bottom w:w="15" w:type="dxa"/><w:right w:w="15" w:type="dxa"/></w:tblCellMar><w:tblLook w:val="04A0" w:firstRow="1" w:lastRow="0" w:firstColumn="1" w:lastColumn="0" w:noHBand="0" w:noVBand="1"/></w:tblPr><w:tblGrid><w:gridCol w:w="709"/><w:gridCol w:w="2133"/><w:gridCol w:w="1317"/><w:gridCol w:w="1290"/><w:gridCol w:w="2883"/></w:tblGrid><w:tr w:rsidR="00EF3070" w14:paraId="2703055B" w14:textId="77777777"><w:trPr><w:trHeight w:val="288"/><w:tblHeader/></w:trPr><w:tc><w:tcPr><w:tcW w:w="709" w:type="dxa"/><w:tcBorders><w:top w:val="single" w:sz="4" w:space="0" w:color="000000"/><w:left w:val="single" w:sz="4" w:space="0" w:color="000000"/><w:bottom w:val="single" w:sz="4" w:space="0" w:color="000000"/><w:right w:val="single" w:sz="4" w:space="0" w:color="000000"/></w:tcBorders><w:vAlign w:val="center"/></w:tcPr><w:p w14:paraId="212E33CE" w14:textId="77777777" w:rsidR="00EF3070" w:rsidRDefault="00000000"><w:pPr><w:spacing w:after="0" w:line="360" w:lineRule="auto"/><w:jc w:val="center"/><w:rPr><w:rFonts w:ascii="Times New Roman" w:hAnsi="Times New Roman" w:cs="Times New Roman"/><w:b/><w:bCs/></w:rPr></w:pPr><w:r><w:rPr><w:rFonts w:ascii="Times New Roman" w:hAnsi="Times New Roman" w:cs="Times New Roman"/><w:b/><w:bCs/></w:rPr><w:t>Sl. No</w:t></w:r></w:p></w:tc><w:tc><w:tcPr><w:tcW w:w="2133" w:type="dxa"/><w:tcBorders><w:top w:val="single" w:sz="4" w:space="0" w:color="000000"/><w:left w:val="single" w:sz="4" w:space="0" w:color="000000"/><w:bottom w:val="single" w:sz="4" w:space="0" w:color="000000"/><w:right w:val="single" w:sz="4" w:space="0" w:color="000000"/></w:tcBorders><w:vAlign w:val="center"/></w:tcPr><w:p w14:paraId="04862AD9" w14:textId="77777777" w:rsidR="00EF3070" w:rsidRDefault="00000000"><w:pPr><w:spacing w:after="0" w:line="360" w:lineRule="auto"/><w:jc w:val="center"/><w:rPr><w:rFonts w:ascii="Times New Roman" w:hAnsi="Times New Roman" w:cs="Times New Roman"/><w:b/><w:bCs/></w:rPr></w:pPr><w:r><w:rPr><w:rFonts w:ascii="Times New Roman" w:hAnsi="Times New Roman" w:cs="Times New Roman"/><w:b/><w:bCs/></w:rPr><w:t>Student Name</w:t></w:r></w:p></w:tc><w:tc><w:tcPr><w:tcW w:w="1317" w:type="dxa"/><w:tcBorders><w:top w:val="single" w:sz="4" w:space="0" w:color="000000"/><w:left w:val="single" w:sz="4" w:space="0" w:color="000000"/><w:bottom w:val="single" w:sz="4" w:space="0" w:color="000000"/><w:right w:val="single" w:sz="4" w:space="0" w:color="000000"/></w:tcBorders><w:vAlign w:val="center"/></w:tcPr><w:p w14:paraId="2A268579" w14:textId="77777777" w:rsidR="00EF3070" w:rsidRDefault="00000000"><w:pPr><w:spacing w:after="0" w:line="360" w:lineRule="auto"/><w:rPr><w:rFonts w:ascii="Times New Roman" w:hAnsi="Times New Roman" w:cs="Times New Roman"/><w:b/><w:bCs/></w:rPr></w:pPr><w:r><w:rPr><w:rFonts w:ascii="Times New Roman" w:hAnsi="Times New Roman" w:cs="Times New Roman"/><w:b/><w:bCs/></w:rPr><w:t>Batch</w:t></w:r></w:p></w:tc><w:tc><w:tcPr><w:tcW w:w="1290" w:type="dxa"/><w:tcBorders><w:top w:val="single" w:sz="4" w:space="0" w:color="000000"/><w:left w:val="single" w:sz="4" w:space="0" w:color="000000"/><w:bottom w:val="single" w:sz="4" w:space="0" w:color="000000"/><w:right w:val="single" w:sz="4" w:space="0" w:color="000000"/></w:tcBorders><w:vAlign w:val="center"/></w:tcPr><w:p w14:paraId="22DB471B" w14:textId="77777777" w:rsidR="00EF3070" w:rsidRDefault="00000000"><w:pPr><w:spacing w:after="0" w:line="360" w:lineRule="auto"/><w:jc w:val="center"/><w:rPr><w:rFonts w:ascii="Times New Roman" w:hAnsi="Times New Roman" w:cs="Times New Roman"/><w:b/><w:bCs/></w:rPr></w:pPr><w:r><w:rPr><w:rFonts w:ascii="Times New Roman" w:hAnsi="Times New Roman" w:cs="Times New Roman"/><w:b/><w:bCs/></w:rPr><w:t>Roll No</w:t></w:r></w:p></w:tc><w:tc><w:tcPr><w:tcW w:w="2883" w:type="dxa"/><w:tcBorders><w:top w:val="single" w:sz="4" w:space="0" w:color="000000"/><w:left w:val="single" w:sz="4" w:space="0" w:color="000000"/><w:bottom w:val="single" w:sz="4" w:space="0" w:color="000000"/><w:right w:val="single" w:sz="4" w:space="0" w:color="000000"/></w:tcBorders><w:vAlign w:val="center"/></w:tcPr><w:p w14:paraId="5143899C" w14:textId="77777777" w:rsidR="00EF3070" w:rsidRDefault="00000000"><w:pPr><w:spacing w:after="0" w:line="360" w:lineRule="auto"/><w:jc w:val="center"/><w:rPr><w:rFonts w:ascii="Times New Roman" w:hAnsi="Times New Roman" w:cs="Times New Roman"/><w:b/><w:bCs/></w:rPr></w:pPr><w:r><w:rPr><w:rFonts w:ascii="Times New Roman" w:hAnsi="Times New Roman" w:cs="Times New Roman"/><w:b/><w:bCs/></w:rPr><w:t>Registration No.</w:t></w:r></w:p></w:tc></w:tr><w:tr w:rsidR="00EF3070" w14:paraId="6AA6CBDD" w14:textId="77777777"><w:trPr><w:trHeight w:val="288"/></w:trPr><w:tc><w:tcPr><w:tcW w:w="709" w:type="dxa"/><w:tcBorders><w:top w:val="single" w:sz="4" w:space="0" w:color="000000"/><w:left w:val="single" w:sz="4" w:space="0" w:color="000000"/><w:bottom w:val="single" w:sz="4" w:space="0" w:color="000000"/><w:right w:val="single" w:sz="4" w:space="0" w:color="000000"/></w:tcBorders><w:vAlign w:val="center"/></w:tcPr><w:p w14:paraId="39F14C2D" w14:textId="77777777" w:rsidR="00EF3070" w:rsidRDefault="00000000"><w:pPr><w:spacing w:after="0" w:line="360" w:lineRule="auto"/><w:rPr><w:rFonts w:ascii="Times New Roman" w:hAnsi="Times New Roman" w:cs="Times New Roman"/></w:rPr></w:pPr><w:r><w:rPr><w:rFonts w:ascii="Times New Roman" w:hAnsi="Times New Roman" w:cs="Times New Roman"/></w:rPr><w:t>1</w:t></w:r></w:p></w:tc><w:tc><w:tcPr><w:tcW w:w="2133" w:type="dxa"/><w:tcBorders><w:top w:val="single" w:sz="4" w:space="0" w:color="000000"/><w:left w:val="single" w:sz="4" w:space="0" w:color="000000"/><w:bottom w:val="single" w:sz="4" w:space="0" w:color="000000"/><w:right w:val="single" w:sz="4" w:space="0" w:color="000000"/></w:tcBorders><w:vAlign w:val="center"/></w:tcPr><w:p w14:paraId="79042533" w14:textId="77777777" w:rsidR="00EF3070" w:rsidRDefault="00000000"><w:pPr><w:spacing w:after="0" w:line="360" w:lineRule="auto"/><w:rPr><w:rFonts w:ascii="Times New Roman" w:hAnsi="Times New Roman" w:cs="Times New Roman"/></w:rPr></w:pPr><w:r><w:rPr><w:rFonts w:ascii="Times New Roman" w:hAnsi="Times New Roman" w:cs="Times New Roman"/></w:rPr><w:t>Prakhar Umrao</w:t></w:r></w:p></w:tc><w:tc><w:tcPr><w:tcW w:w="1317" w:type="dxa"/><w:tcBorders><w:top w:val="single" w:sz="4" w:space="0" w:color="000000"/><w:left w:val="single" w:sz="4" w:space="0" w:color="000000"/><w:bottom w:val="single" w:sz="4" w:space="0" w:color="000000"/><w:right w:val="single" w:sz="4" w:space="0" w:color="000000"/></w:tcBorders></w:tcPr><w:p w14:paraId="2F1400FA" w14:textId="77777777" w:rsidR="00EF3070" w:rsidRDefault="00000000"><w:pPr><w:spacing w:after="0" w:line="360" w:lineRule="auto"/><w:rPr><w:rFonts w:ascii="Times New Roman" w:hAnsi="Times New Roman" w:cs="Times New Roman"/></w:rPr></w:pPr><w:r><w:rPr><w:rFonts w:ascii="Times New Roman" w:hAnsi="Times New Roman" w:cs="Times New Roman"/></w:rPr><w:t>A2</w:t></w:r></w:p></w:tc><w:tc><w:tcPr><w:tcW w:w="1290" w:type="dxa"/><w:tcBorders><w:top w:val="single" w:sz="4" w:space="0" w:color="000000"/><w:left w:val="single" w:sz="4" w:space="0" w:color="000000"/><w:bottom w:val="single" w:sz="4" w:space="0" w:color="000000"/><w:right w:val="single" w:sz="4" w:space="0" w:color="000000"/></w:tcBorders><w:vAlign w:val="center"/></w:tcPr><w:p w14:paraId="2D763C94" w14:textId="77777777" w:rsidR="00EF3070" w:rsidRDefault="00000000"><w:pPr><w:spacing w:after="0" w:line="360" w:lineRule="auto"/><w:rPr><w:rFonts w:ascii="Times New Roman" w:hAnsi="Times New Roman" w:cs="Times New Roman"/></w:rPr></w:pPr><w:r><w:rPr><w:rFonts w:ascii="Times New Roman" w:hAnsi="Times New Roman" w:cs="Times New Roman"/></w:rPr><w:t>41</w:t></w:r></w:p></w:tc><w:tc><w:tcPr><w:tcW w:w="2883" w:type="dxa"/><w:tcBorders><w:top w:val="single" w:sz="4" w:space="0" w:color="000000"/><w:left w:val="single" w:sz="4" w:space="0" w:color="000000"/><w:bottom w:val="single" w:sz="4" w:space="0" w:color="000000"/><w:right w:val="single" w:sz="4" w:space="0" w:color="000000"/></w:tcBorders></w:tcPr><w:p w14:paraId="2BFED7BA" w14:textId="77777777" w:rsidR="00EF3070" w:rsidRDefault="00000000"><w:pPr><w:spacing w:after="0" w:line="360" w:lineRule="auto"/><w:rPr><w:rFonts w:ascii="Times New Roman" w:hAnsi="Times New Roman" w:cs="Times New Roman"/></w:rPr></w:pPr><w:r><w:rPr><w:rFonts w:ascii="Times New Roman" w:hAnsi="Times New Roman" w:cs="Times New Roman"/></w:rPr><w:t>230962210</w:t></w:r></w:p></w:tc></w:tr><w:tr w:rsidR="00EF3070" w14:paraId="5A0284E4" w14:textId="77777777"><w:trPr><w:trHeight w:val="288"/></w:trPr><w:tc><w:tcPr><w:tcW w:w="709" w:type="dxa"/><w:tcBorders><w:top w:val="single" w:sz="4" w:space="0" w:color="000000"/><w:left w:val="single" w:sz="4" w:space="0" w:color="000000"/><w:bottom w:val="single" w:sz="4" w:space="0" w:color="000000"/><w:right w:val="single" w:sz="4" w:space="0" w:color="000000"/></w:tcBorders><w:vAlign w:val="center"/></w:tcPr><w:p w14:paraId="1BE7E090" w14:textId="77777777" w:rsidR="00EF3070" w:rsidRDefault="00000000"><w:pPr><w:spacing w:after="0" w:line="360" w:lineRule="auto"/><w:rPr><w:rFonts w:ascii="Times New Roman" w:hAnsi="Times New Roman" w:cs="Times New Roman"/></w:rPr></w:pPr><w:r><w:rPr><w:rFonts w:ascii="Times New Roman" w:hAnsi="Times New Roman" w:cs="Times New Roman"/></w:rPr><w:t>2</w:t></w:r></w:p></w:tc><w:tc><w:tcPr><w:tcW w:w="2133" w:type="dxa"/><w:tcBorders><w:top w:val="single" w:sz="4" w:space="0" w:color="000000"/><w:left w:val="single" w:sz="4" w:space="0" w:color="000000"/><w:bottom w:val="single" w:sz="4" w:space="0" w:color="000000"/><w:right w:val="single" w:sz="4" w:space="0" w:color="000000"/></w:tcBorders><w:vAlign w:val="center"/></w:tcPr><w:p w14:paraId="299EB0C8" w14:textId="77777777" w:rsidR="00EF3070" w:rsidRDefault="00000000"><w:pPr><w:spacing w:after="0" w:line="360" w:lineRule="auto"/><w:rPr><w:rFonts w:ascii="Times New Roman" w:hAnsi="Times New Roman" w:cs="Times New Roman"/></w:rPr></w:pPr><w:r><w:rPr><w:rFonts w:ascii="Times New Roman" w:hAnsi="Times New Roman" w:cs="Times New Roman"/></w:rPr><w:t>Devansh Singh</w:t></w:r></w:p></w:tc><w:tc><w:tcPr><w:tcW w:w="1317" w:type="dxa"/><w:tcBorders><w:top w:val="single" w:sz="4" w:space="0" w:color="000000"/><w:left w:val="single" w:sz="4" w:space="0" w:color="000000"/><w:bottom w:val="single" w:sz="4" w:space="0" w:color="000000"/><w:right w:val="single" w:sz="4" w:space="0" w:color="000000"/></w:tcBorders></w:tcPr><w:p w14:paraId="47F0B289" w14:textId="77777777" w:rsidR="00EF3070" w:rsidRDefault="00000000"><w:pPr><w:spacing w:after="0" w:line="360" w:lineRule="auto"/><w:rPr><w:rFonts w:ascii="Times New Roman" w:hAnsi="Times New Roman" w:cs="Times New Roman"/></w:rPr></w:pPr><w:r><w:rPr><w:rFonts w:ascii="Times New Roman" w:hAnsi="Times New Roman" w:cs="Times New Roman"/></w:rPr><w:t>A2</w:t></w:r></w:p></w:tc><w:tc><w:tcPr><w:tcW w:w="1290" w:type="dxa"/><w:tcBorders><w:top w:val="single" w:sz="4" w:space="0" w:color="000000"/><w:left w:val="single" w:sz="4" w:space="0" w:color="000000"/><w:bottom w:val="single" w:sz="4" w:space="0" w:color="000000"/><w:right w:val="single" w:sz="4" w:space="0" w:color="000000"/></w:tcBorders><w:vAlign w:val="center"/></w:tcPr><w:p w14:paraId="77FE0F5A" w14:textId="77777777" w:rsidR="00EF3070" w:rsidRDefault="00000000"><w:pPr><w:spacing w:after="0" w:line="360" w:lineRule="auto"/><w:rPr><w:rFonts w:ascii="Times New Roman" w:hAnsi="Times New Roman" w:cs="Times New Roman"/></w:rPr></w:pPr><w:r><w:rPr><w:rFonts w:ascii="Times New Roman" w:hAnsi="Times New Roman" w:cs="Times New Roman"/></w:rPr><w:t>40</w:t></w:r></w:p></w:tc><w:tc><w:tcPr><w:tcW w:w="2883" w:type="dxa"/><w:tcBorders><w:top w:val="single" w:sz="4" w:space="0" w:color="000000"/><w:left w:val="single" w:sz="4" w:space="0" w:color="000000"/><w:bottom w:val="single" w:sz="4" w:space="0" w:color="000000"/><w:right w:val="single" w:sz="4" w:space="0" w:color="000000"/></w:tcBorders></w:tcPr><w:p w14:paraId="689FEAE0" w14:textId="77777777" w:rsidR="00EF3070" w:rsidRDefault="00000000"><w:pPr><w:spacing w:after="0" w:line="360" w:lineRule="auto"/><w:rPr><w:rFonts w:ascii="Times New Roman" w:hAnsi="Times New Roman" w:cs="Times New Roman"/></w:rPr></w:pPr><w:r><w:rPr><w:rFonts w:ascii="Times New Roman" w:hAnsi="Times New Roman" w:cs="Times New Roman"/></w:rPr><w:t>230962208</w:t></w:r></w:p></w:tc></w:tr><w:tr w:rsidR="00EF3070" w14:paraId="6DFC936C" w14:textId="77777777"><w:trPr><w:trHeight w:val="288"/></w:trPr><w:tc><w:tcPr><w:tcW w:w="709" w:type="dxa"/><w:tcBorders><w:top w:val="single" w:sz="4" w:space="0" w:color="000000"/><w:left w:val="single" w:sz="4" w:space="0" w:color="000000"/><w:bottom w:val="single" w:sz="4" w:space="0" w:color="000000"/><w:right w:val="single" w:sz="4" w:space="0" w:color="000000"/></w:tcBorders><w:vAlign w:val="center"/></w:tcPr><w:p w14:paraId="2DB0FFC9" w14:textId="77777777" w:rsidR="00EF3070" w:rsidRDefault="00000000"><w:pPr><w:spacing w:after="0" w:line="360" w:lineRule="auto"/><w:rPr><w:rFonts w:ascii="Times New Roman" w:hAnsi="Times New Roman" w:cs="Times New Roman"/></w:rPr></w:pPr><w:r><w:rPr><w:rFonts w:ascii="Times New Roman" w:hAnsi="Times New Roman" w:cs="Times New Roman"/></w:rPr><w:t>3</w:t></w:r></w:p></w:tc><w:tc><w:tcPr><w:tcW w:w="2133" w:type="dxa"/><w:tcBorders><w:top w:val="single" w:sz="4" w:space="0" w:color="000000"/><w:left w:val="single" w:sz="4" w:space="0" w:color="000000"/><w:bottom w:val="single" w:sz="4" w:space="0" w:color="000000"/><w:right w:val="single" w:sz="4" w:space="0" w:color="000000"/></w:tcBorders><w:vAlign w:val="center"/></w:tcPr><w:p w14:paraId="7A519D81" w14:textId="77777777" w:rsidR="00EF3070" w:rsidRDefault="00000000"><w:pPr><w:spacing w:after="0" w:line="360" w:lineRule="auto"/><w:rPr><w:rFonts w:ascii="Times New Roman" w:hAnsi="Times New Roman" w:cs="Times New Roman"/></w:rPr></w:pPr><w:proofErr w:type="spellStart"/><w:r><w:rPr><w:rFonts w:ascii="Times New Roman" w:hAnsi="Times New Roman" w:cs="Times New Roman"/></w:rPr><w:t>Komaravolu</w:t></w:r><w:proofErr w:type="spellEnd"/><w:r><w:rPr><w:rFonts w:ascii="Times New Roman" w:hAnsi="Times New Roman" w:cs="Times New Roman"/></w:rPr><w:t xml:space="preserve"> Aashrith </w:t></w:r><w:proofErr w:type="spellStart"/><w:r><w:rPr><w:rFonts w:ascii="Times New Roman" w:hAnsi="Times New Roman" w:cs="Times New Roman"/></w:rPr><w:t>Saradhi</w:t></w:r><w:proofErr w:type="spellEnd"/></w:p></w:tc><w:tc><w:tcPr><w:tcW w:w="1317" w:type="dxa"/><w:tcBorders><w:top w:val="single" w:sz="4" w:space="0" w:color="000000"/><w:left w:val="single" w:sz="4" w:space="0" w:color="000000"/><w:bottom w:val="single" w:sz="4" w:space="0" w:color="000000"/><w:right w:val="single" w:sz="4" w:space="0" w:color="000000"/></w:tcBorders></w:tcPr><w:p w14:paraId="281455C0" w14:textId="77777777" w:rsidR="00EF3070" w:rsidRDefault="00000000"><w:pPr><w:spacing w:after="0" w:line="360" w:lineRule="auto"/><w:rPr><w:rFonts w:ascii="Times New Roman" w:hAnsi="Times New Roman" w:cs="Times New Roman"/></w:rPr></w:pPr><w:r><w:rPr><w:rFonts w:ascii="Times New Roman" w:hAnsi="Times New Roman" w:cs="Times New Roman"/></w:rPr><w:t>A2</w:t></w:r></w:p></w:tc><w:tc><w:tcPr><w:tcW w:w="1290" w:type="dxa"/><w:tcBorders><w:top w:val="single" w:sz="4" w:space="0" w:color="000000"/><w:left w:val="single" w:sz="4" w:space="0" w:color="000000"/><w:bottom w:val="single" w:sz="4" w:space="0" w:color="000000"/><w:right w:val="single" w:sz="4" w:space="0" w:color="000000"/></w:tcBorders><w:vAlign w:val="center"/></w:tcPr><w:p w14:paraId="2F2A7234" w14:textId="77777777" w:rsidR="00EF3070" w:rsidRDefault="00000000"><w:pPr><w:spacing w:after="0" w:line="360" w:lineRule="auto"/><w:rPr><w:rFonts w:ascii="Times New Roman" w:hAnsi="Times New Roman" w:cs="Times New Roman"/></w:rPr></w:pPr><w:r><w:rPr><w:rFonts w:ascii="Times New Roman" w:hAnsi="Times New Roman" w:cs="Times New Roman"/></w:rPr><w:t>39</w:t></w:r></w:p></w:tc><w:tc><w:tcPr><w:tcW w:w="2883" w:type="dxa"/><w:tcBorders><w:top w:val="single" w:sz="4" w:space="0" w:color="000000"/><w:left w:val="single" w:sz="4" w:space="0" w:color="000000"/><w:bottom w:val="single" w:sz="4" w:space="0" w:color="000000"/><w:right w:val="single" w:sz="4" w:space="0" w:color="000000"/></w:tcBorders></w:tcPr><w:p w14:paraId="0A6C0B5D" w14:textId="77777777" w:rsidR="00EF3070" w:rsidRDefault="00000000"><w:pPr><w:spacing w:after="0" w:line="360" w:lineRule="auto"/><w:rPr><w:rFonts w:ascii="Times New Roman" w:hAnsi="Times New Roman" w:cs="Times New Roman"/></w:rPr></w:pPr><w:r><w:rPr><w:rFonts w:ascii="Times New Roman" w:hAnsi="Times New Roman" w:cs="Times New Roman"/></w:rPr><w:t>230962196</w:t></w:r></w:p></w:tc></w:tr></w:tbl><w:p w14:paraId="0DB08F9F" w14:textId="77777777" w:rsidR="00EF3070" w:rsidRDefault="00EF3070"><w:pPr><w:spacing w:after="0" w:line="360" w:lineRule="auto"/><w:rPr><w:rFonts w:ascii="Times New Roman" w:hAnsi="Times New Roman" w:cs="Times New Roman"/></w:rPr></w:pPr></w:p><w:sectPr w:rsidR="00EF3070"><w:pgSz w:w="12240" w:h="15840"/><w:pgMar w:top="1440" w:right="1440" w:bottom="1440" w:left="1440" w:header="0" w:footer="0" w:gutter="0"/><w:cols w:space="720"/><w:formProt w:val="0"/><w:docGrid w:linePitch="360"/></w:sectPr></w:body></w:document>